MANIFEST.in
NEWS.txt
README.txt
setup.py
src/modern_package/__init__.py
src/modern_package/templates/.gitignore
src/modern_package/templates/.hgignore
src/modern_package/templates/.namespace__init__.py
src/modern_package/templates/.normal__init__.py
src/modern_package/templates/HACKING.txt
src/modern_package/templates/MANIFEST.in
src/modern_package/templates/NEWS.txt
src/modern_package/templates/README.rst
src/modern_package/templates/bootstrap.py
src/modern_package/templates/buildout.cfg_tmpl
src/modern_package/templates/setup.py_tmpl
src/modern_package_template.egg-info/PKG-INFO
src/modern_package_template.egg-info/SOURCES.txt
src/modern_package_template.egg-info/dependency_links.txt
src/modern_package_template.egg-info/entry_points.txt
src/modern_package_template.egg-info/not-zip-safe
src/modern_package_template.egg-info/requires.txt
src/modern_package_template.egg-info/top_level.txt