Metadata-Version: 1.0
Name: modern-package-template
Version: 1.0
Summary: PasteScript template to create a Python project with distribute and buildout support
Home-page: http://bitbucket.org/srid/modern-package-template/
Author: Sridhar Ratnakumar
Author-email: srid@nearfar.org
License: GNU General Public License v3
Platform: UNKNOWN
Classifier: Development Status :: 5 - Production/Stable
Classifier: Environment :: Console
Classifier: Environment :: Plugins
Classifier: Framework :: Paste
Classifier: Intended Audience :: Developers
Classifier: License :: OSI Approved :: GNU General Public License (GPL)
Classifier: Operating System :: OS Independent
Classifier: Programming Language :: Python
Classifier: Topic :: Software Development :: Code Generators
